nonebot_plugin_heweather/__init__.py
nonebot_plugin_heweather/config.py
nonebot_plugin_heweather/model.py
nonebot_plugin_heweather/render_pic.py
nonebot_plugin_heweather/types.py
nonebot_plugin_heweather/utils.py
nonebot_plugin_heweather/weather_data.py
nonebot_plugin_heweather/templates/weather.html
nonebot_plugin_heweather/templates/css/qweather-icons.css
nonebot_plugin_heweather/templates/css/qweather-icons.json
nonebot_plugin_heweather/templates/css/weather.css
nonebot_plugin_heweather/templates/css/fonts/qweather-icons.ttf
nonebot_plugin_heweather/templates/css/fonts/qweather-icons.woff
nonebot_plugin_heweather/templates/css/fonts/qweather-icons.woff2
nonebot_plugin_heweather-0.9.0.dist-info/METADATA
nonebot_plugin_heweather-0.9.0.dist-info/WHEEL
nonebot_plugin_heweather-0.9.0.dist-info/licenses/LICENSE
nonebot_plugin_heweather-0.9.0.dist-info/RECORD
