Metadata-Version: 2.4
Name: nonebot-plugin-heweather
Version: 0.9.0
Summary: Get Heweather information and convert to pictures
Project-URL: Homepage, https://github.com/kexue-z/nonebot-plugin-heweather
Project-URL: Bug Tracker, https://github.com/kexue-z/nonebot-plugin-heweather/issues
Author-email: kexue-z <x@kexue-cloud.cn>
License: MIT License
License-File: LICENSE
Requires-Python: >=3.10
Requires-Dist: httpx>=0.28.1
Requires-Dist: nonebot-plugin-alconna>=0.57.0
Requires-Dist: nonebot-plugin-htmlrender>=0.6.0
Requires-Dist: nonebot2>=2.4.0
Requires-Dist: pyjwt[crypto]>=2.10.1
